acouspike/__init__.py
acouspike/ASR/__init__.py
acouspike/ASR/asr.py
acouspike/ASR/bin/__init__.py
acouspike/ASR/bin/asr_inference.py
acouspike/ASR/bin/asr_train.py
acouspike/ASR/encoder/SRNN.py
acouspike/ASR/encoder/__init__.py
acouspike/ASR/encoder/vgg_rnn_encoder.py
acouspike/models/__init__.py
acouspike/models/model_warpper.py
acouspike/models/layers/__init__.py
acouspike/models/layers/base.py
acouspike/models/layers/layer.py
acouspike/models/network/SSM.py
acouspike/models/network/Spikeformer.py
acouspike/models/network/SpikingNet.py
acouspike/models/network/Spiking_LSTM.py
acouspike/models/network/TCN.py
acouspike/models/network/__init__.py
acouspike/models/network/utils.py
acouspike/models/neuron/S4DModule.py
acouspike/models/neuron/__init__.py
acouspike/models/neuron/base_neuron.py
acouspike/models/neuron/lif.py
acouspike/models/neuron/membrane_update.py
acouspike/models/neuron/neuron.py
acouspike/models/surrogate/ASGL_surrogate.py
acouspike/models/surrogate/__init__.py
acouspike/models/surrogate/surrogate.py
acouspike/src/__init__.py
acouspike/src/accelerate.py
acouspike/src/logger.py
acouspike/src/optimization.py
acouspike/src/trainer.py
acouspike/src/trainer_args.py
acouspike/src/trainer_utils.py
acouspike/src/utils.py
acouspike-0.0.0.1.dist-info/METADATA
acouspike-0.0.0.1.dist-info/WHEEL
acouspike-0.0.0.1.dist-info/top_level.txt
acouspike-0.0.0.1.dist-info/RECORD
