Metadata-Version: 2.2
Name: acouspike
Version: 0.0.0.1
Summary: A package for acoustic spike analysis
Home-page: https://github.com/ZhangShimin1/AcouSpike
Author: Zeyang Song
Author-email: zeyang_song@u.nus.edu
Classifier: Programming Language :: Python :: 3 :: Only
Classifier: Programming Language :: Python :: 3.6
Classifier: Programming Language :: Python :: 3.7
Classifier: Programming Language :: Python :: 3.8
Classifier: License :: Other/Proprietary License
Classifier: Operating System :: OS Independent
Requires-Python: >=3.6
Dynamic: author
Dynamic: author-email
Dynamic: classifier
Dynamic: description
Dynamic: description-content-type
Dynamic: home-page
Dynamic: requires-python
Dynamic: summary
